{"custom_forms_fields":{"contact-form-with-full-address-name":{"label":"Full Name","name":"contact-form-with-full-address-name","type":"text","description":"","default_value":"","minimum_value":"0","maximum_value":"100","steps_count":"1","file_types":"","upload_size":"","max_upload_files":"","placeholder":"e.g. John","options":"{\"label\":[\"\",\"\"],\"value\":[\"\",\"\"]}","char_limit":"","filter_post_types":"","filter_taxonomy":"","filter_user_roles":"","rel_attr":"do-follow","appearance":"","required":"1","validation_msg":"Provide the requested data","files_save":"ids","files_save_separator":"array","id":"cwp_field_151922516498","class":"","container_class":"","conditional_field":"cwp_field_364089721627","conditional_operator":"","conditional_value":"","group_id":"6"},"contact-form-with-full-address-email":{"label":"Email","name":"contact-form-with-full-address-email","type":"email","description":"","default_value":"","minimum_value":"0","maximum_value":"100","steps_count":"1","file_types":"","upload_size":"","max_upload_files":"","placeholder":"e.g. John@cubewp.com","options":"{\"label\":[\"\",\"\"],\"value\":[\"\",\"\"]}","char_limit":"","filter_post_types":"","filter_taxonomy":"","filter_user_roles":"","rel_attr":"do-follow","appearance":"","required":"1","validation_msg":"Provide the requested data","files_save":"ids","files_save_separator":"array","id":"cwp_field_702300113947","class":"","container_class":"","conditional_field":"cwp_field_794524747797","conditional_operator":"","conditional_value":"","group_id":"6"},"contact-form-with-full-address-number":{"label":"Phone Number","name":"contact-form-with-full-address-number","type":"number","description":"","default_value":"","minimum_value":"0","maximum_value":"100","steps_count":"1","file_types":"","upload_size":"","max_upload_files":"","placeholder":"e.g. 555 5551234","options":"{\"label\":[\"\",\"\"],\"value\":[\"\",\"\"]}","char_limit":"","filter_post_types":"","filter_taxonomy":"","filter_user_roles":"","rel_attr":"do-follow","appearance":"","validation_msg":"","files_save":"ids","files_save_separator":"array","id":"cwp_field_723819698699","class":"","container_class":"","conditional_field":"cwp_field_794524747797","conditional_operator":"","conditional_value":"","group_id":"6"},"contact-form-with-full-address-street":{"label":"Street Address","name":"contact-form-with-full-address-street","type":"text","description":"","default_value":"","minimum_value":"0","maximum_value":"100","steps_count":"1","file_types":"","upload_size":"","max_upload_files":"","placeholder":"e.g. 13th street ","options":"{\"label\":[\"\",\"\"],\"value\":[\"\",\"\"]}","char_limit":"","filter_post_types":"","filter_taxonomy":"","filter_user_roles":"","rel_attr":"do-follow","appearance":"","validation_msg":"","files_save":"ids","files_save_separator":"array","id":"cwp_field_954688490399","class":"","container_class":"","conditional_field":"cwp_field_794524747797","conditional_operator":"","conditional_value":"","group_id":"6"},"contact-form-with-full-address-state":{"label":"State\/Province","name":"contact-form-with-full-address-state","type":"text","description":"","default_value":"","minimum_value":"0","maximum_value":"100","steps_count":"1","file_types":"","upload_size":"","max_upload_files":"","placeholder":"e.g. Arizona","options":"{\"label\":[\"\",\"\"],\"value\":[\"\",\"\"]}","char_limit":"","filter_post_types":"","filter_taxonomy":"","filter_user_roles":"","rel_attr":"do-follow","appearance":"","validation_msg":"","files_save":"ids","files_save_separator":"array","id":"cwp_field_6831331906","class":"","container_class":"","conditional_field":"cwp_field_794524747797","conditional_operator":"","conditional_value":"","group_id":"6"},"contact-form-with-full-address-zipcode":{"label":"ZIP\/Postal Code","name":"contact-form-with-full-address-zipcode","type":"text","description":"","default_value":"","minimum_value":"0","maximum_value":"100","steps_count":"1","file_types":"","upload_size":"","max_upload_files":"","placeholder":"e.g. 85142","options":"{\"label\":[\"\",\"\"],\"value\":[\"\",\"\"]}","char_limit":"","filter_post_types":"","filter_taxonomy":"","filter_user_roles":"","rel_attr":"do-follow","appearance":"","validation_msg":"","files_save":"ids","files_save_separator":"array","id":"cwp_field_891830014795","class":"","container_class":"","conditional_field":"cwp_field_794524747797","conditional_operator":"","conditional_value":"","group_id":"6"},"contact-form-with-full-address-country":{"label":"Country","name":"contact-form-with-full-address-country","type":"text","description":"","default_value":"","minimum_value":"0","maximum_value":"100","steps_count":"1","file_types":"","upload_size":"","max_upload_files":"","placeholder":"e.g. USA","options":"{\"label\":[\"\",\"\"],\"value\":[\"\",\"\"]}","char_limit":"","filter_post_types":"","filter_taxonomy":"","filter_user_roles":"","rel_attr":"do-follow","appearance":"","validation_msg":"","files_save":"ids","files_save_separator":"array","id":"cwp_field_187775283414","class":"","container_class":"","conditional_field":"cwp_field_794524747797","conditional_operator":"","conditional_value":"","group_id":"6"},"contact-form-with-full-address-message":{"label":"Message","name":"contact-form-with-full-address-message","type":"textarea","description":"","default_value":"","minimum_value":"0","maximum_value":"100","steps_count":"1","file_types":"","upload_size":"","max_upload_files":"","placeholder":"e.g. I want to say","options":"{\"label\":[\"\",\"\"],\"value\":[\"\",\"\"]}","char_limit":"","filter_post_types":"","filter_taxonomy":"","filter_user_roles":"","rel_attr":"do-follow","appearance":"","validation_msg":"","files_save":"ids","files_save_separator":"array","id":"cwp_field_2297749891","class":"","container_class":"","conditional_field":"cwp_field_794524747797","conditional_operator":"","conditional_value":"","group_id":"6"},"contact-form-with-full-address-terms":{"label":"Terms & Conditions","name":"contact-form-with-full-address-terms","type":"checkbox","description":"","default_value":"","minimum_value":"0","maximum_value":"100","steps_count":"1","file_types":"","upload_size":"","max_upload_files":"","placeholder":"","options":"{\"label\":[\"I Agree the terms & conditions\",\"\"],\"value\":[\"i_agree_with_terms\",\"\"]}","char_limit":"","filter_post_types":"","filter_taxonomy":"","filter_user_roles":"","rel_attr":"do-follow","appearance":"","required":"1","validation_msg":"Please Accept our Terms and Conditions","files_save":"ids","files_save_separator":"array","id":"cwp_field_44005579007","class":"","container_class":"","conditional_field":"cwp_field_794524747797","conditional_operator":"","conditional_value":"","group_id":"6"}}}